{
	"partitions" : [
		{
			"name" : "Top",
			"pins" : [
				{
					"name" : "wifi_tx",
					"strict" : false
				},
				{
					"name" : "uart_tx",
					"strict" : false
				},
				{
					"name" : "scl",
					"strict" : false
				},
				{
					"name" : "rck",
					"strict" : false
				},
				{
					"name" : "sck",
					"strict" : false
				},
				{
					"name" : "din",
					"strict" : false
				},
				{
					"name" : "lcd_rst",
					"strict" : false
				},
				{
					"name" : "lcd_dc",
					"strict" : false
				},
				{
					"name" : "lcd_sclk",
					"strict" : false
				},
				{
					"name" : "lcd_mosi",
					"strict" : false
				},
				{
					"name" : "lcd_cs",
					"strict" : false
				},
				{
					"name" : "sda",
					"strict" : false
				},
				{
					"name" : "wifi_rx",
					"strict" : false
				},
				{
					"name" : "clk",
					"strict" : false
				},
				{
					"name" : "reset",
					"strict" : false
				}
			]
		}
	]
}